saml2idp
