Metadata-Version: 1.0
Name: saml2idp
Version: 0.17
Summary: SAML 2.0 IdP for Django
Home-page: http://code.google.com/p/django-saml2-idp/
Author: John Samuel Anderson
Author-email: john@andersoninnovative.com
License: MIT
Platform: UNKNOWN
